COPYING
MANIFEST.in
README.md
setup.py
call/__init__.py
call/tests.py
call.egg-info/PKG-INFO
call.egg-info/SOURCES.txt
call.egg-info/dependency_links.txt
call.egg-info/top_level.txt