Metadata-Version: 1.1
Name: call
Version: 0.1
Summary: Pure-python reimplementation of python call semantics
Home-page: https://github.com/zyga/call/
Author: Zygmunt Krynicki
Author-email: zygmunt.krynicki@canonical.com
License: LGPL
Platform: UNKNOWN
Classifier: Development Status :: 4 - Beta
Classifier: Intended Audience :: Developers
Classifier: License :: OSI Approved :: GNU Lesser General Public License v3 or later (LGPLv3+)
Classifier: Programming Language :: Python :: 3
Classifier: Programming Language :: Python :: 3.1
Classifier: Programming Language :: Python :: 3.2
Classifier: Programming Language :: Python :: 3.3
Classifier: Topic :: Software Development :: Libraries :: Python Modules
